pymarkdown_document/__init__.py
pymarkdown_document/markdown_document.py
pymarkdown_document/markdown_tokens.py
pymarkdown_document-0.1.0.dist-info/LICENSE
pymarkdown_document-0.1.0.dist-info/METADATA
pymarkdown_document-0.1.0.dist-info/WHEEL
pymarkdown_document-0.1.0.dist-info/RECORD
