Metadata-Version: 2.1
Name: pymarkdown-document
Version: 0.1.0
Summary: Write markdown documents with a fluent API.
License: GPL-3.0-only
Author: Demetrius Panovitch
Author-email: demetrius.mp789@gmail.com
Requires-Python: >=3.10,<4.0
Classifier: License :: OSI Approved :: GNU General Public License v3 (GPLv3)
Classifier: Programming Language :: Python :: 3
Classifier: Programming Language :: Python :: 3.10
Classifier: Programming Language :: Python :: 3.11
Requires-Dist: typing-extensions (>=4.7.0,<5.0.0)
Project-URL: Documentation, https://pymarkdown-document.readthedocs.io/en/latest/
Project-URL: Issue Tracker, https://github.com/demetrius-mp/pymarkdown-document/issues
Project-URL: Source Code, https://github.com/demetrius-mp/pymarkdown-document
